NXSP_to_xyz/NXSP_to_xyz.py
NXSP_to_xyz/__init__.py
NXSP_to_xyz-0.0.2.dist-info/LICENSE.txt
NXSP_to_xyz-0.0.2.dist-info/METADATA
NXSP_to_xyz-0.0.2.dist-info/WHEEL
NXSP_to_xyz-0.0.2.dist-info/top_level.txt
NXSP_to_xyz-0.0.2.dist-info/RECORD
